{
    "products": [
        {
            "name": "Macarrão",
            "price": "8.99",
            "id": 1
        },
        {
            "name": "Arroz",
            "price": "6.34",
            "id": 2
        },
        {
            "name": "Feijão",
            "price": "9.40",
            "id": 3
        },
        {
            "name": "Farinha",
            "price": "6.55",
            "id": 4
        },
        {
            "name": "Batata",
            "price": "3.45",
            "id": 5
        }
    ]
}
